{
	"type": "lecture",
	"id": "110",
	"content_type": "video",
	"property_keys": ["type", "id", "content_type"],
	"title": {
		"ru": "Module 6: Creating a Networking Environment",
		"kk": "Module 6: Creating a Networking Environment",
		"en": "Module 6: Creating a Networking Environment"
	},
	"files_list": [
		{
			"path": "metadata.json",
			"type": "metadata",
			"lang": "en"
		},
		{
			"path": "video/ru/video.mp4",
			"type": "video",
			"lang": "ru"
		},
		{
			"path": "presentation/presentation.en.pptx",
			"type": "presentation",
			"lang": "en"
		},
		{
			"path": "chapters/chapters.en.vtt",
      		"type": "chapters",
      		"lang": "en"
		},
		{
			"path": "subtitles/subtitles.kk.vtt",
			"type": "subtitles",
			"lang": "kk"
		},
		{
			"path": "subtitles/subtitles.ru.vtt",
      		"type": "subtitles",
      		"lang": "ru"
		}
	]
}